emi/__init__.py
emi/__main__.py
emi/emi.py
emi-0.0.16.dist-info/METADATA
emi-0.0.16.dist-info/WHEEL
emi-0.0.16.dist-info/entry_points.txt
emi-0.0.16.dist-info/top_level.txt
emi-0.0.16.dist-info/RECORD
