Metadata-Version: 2.1
Name: emi
Version: 0.0.16
Summary: Eons Modular Installer
Home-page: https://github.com/eons-dev/bin_emi
Author: eons
Author-email: support@eons.llc
Project-URL: Bug Tracker, https://github.com/eons-dev/bin_emi/issues
Classifier: Programming Language :: Python :: 3
Classifier: License :: OSI Approved :: MIT License
Classifier: Operating System :: OS Independent
Classifier: Development Status :: 3 - Alpha
Requires-Python: >=3.7
Requires-Dist: eot
Requires-Dist: jsonpickle
Requires-Dist: eons
Requires-Dist: ebbs
Requires-Dist: sqlalchemy
